sphinx_pcap/__init__.py
sphinx_pcap-0.2.1.dist-info/LICENSE
sphinx_pcap-0.2.1.dist-info/METADATA
sphinx_pcap-0.2.1.dist-info/WHEEL
sphinx_pcap-0.2.1.dist-info/top_level.txt
sphinx_pcap-0.2.1.dist-info/RECORD
