Metadata-Version: 2.1
Name: sphinx-pcap
Version: 0.2.1
Summary: Sphinx support for displaying pcap files
Home-page: https://github.com/jinjamator/sphinx_pcap
Author: Wilhelm Putz, CANCOM Austria AG
Author-email: jinjamator@aci.guru
License: UNKNOWN
Keywords: sphinx extension pcap tshark tcpdump
Platform: any
Classifier: License :: OSI Approved :: Apache Software License
Classifier: Programming Language :: Python :: 3.7
Classifier: Programming Language :: Python :: 3.8
Classifier: Framework :: Sphinx :: Extension
Classifier: Natural Language :: English
License-File: LICENSE
Requires-Dist: docutils
Requires-Dist: sphinx
